CGCD/__init__.py
CGCD/analyzetools.py
cgcd-0.0.2.dist-info/licenses/LICENCE.txt
cgcd-0.0.2.dist-info/METADATA
cgcd-0.0.2.dist-info/WHEEL
cgcd-0.0.2.dist-info/top_level.txt
cgcd-0.0.2.dist-info/RECORD
