Metadata-Version: 2.4
Name: CGCD
Version: 0.0.2
Summary: Computer Glow Curve Deconvolution
Home-page: https://github.com/JFBenavente/CGCD
Author: JF Benavente, JE Tenopala
Author-email: jf.benavente@ciemat.es, jtenopalap1800@alumno.ipn.mx
License: MIT
Classifier: Programming Language :: Python :: 3
Classifier: License :: OSI Approved :: MIT License
Classifier: Operating System :: OS Independent
Requires-Python: >=3.7
License-File: LICENCE.txt
Requires-Dist: numpy
Requires-Dist: pandas
Requires-Dist: matplotlib
Requires-Dist: scipy
Requires-Dist: plotly
Requires-Dist: openpyxl
Dynamic: author
Dynamic: author-email
Dynamic: classifier
Dynamic: description
Dynamic: description-content-type
Dynamic: home-page
Dynamic: license
Dynamic: license-file
Dynamic: requires-dist
Dynamic: requires-python
Dynamic: summary
